cognitive_core/__init__.py
cognitive_core/cognitive_base.py
cognitive_core/cognitive_checkpoint.py
cognitive_core/cognitive_modules.py
cognitive_core/cognitive_training.py
cognitive_core/cognitive_utils.py
cognitive_core/setup.py
cognitive_cores-1.0.3.dist-info/METADATA
cognitive_cores-1.0.3.dist-info/WHEEL
cognitive_cores-1.0.3.dist-info/top_level.txt
cognitive_cores-1.0.3.dist-info/RECORD
