Metadata-Version: 2.4
Name: cognitive-cores
Version: 1.0.3
Summary: Universal Cognitive Architecture Framework for AI Models
Home-page: https://github.com/Volgat/nexus-standardisation
Author: Mike Amega
Author-email: Mike Amega <contact@amewebstudio.com>
License: Proprietary
Project-URL: Homepage, https://github.com/Volgat/nexus-standardisation
Project-URL: HuggingFace, https://huggingface.co/amewebstudio/cognitive-core
Project-URL: Documentation, https://github.com/Volgat/nexus-standardisation#readme
Project-URL: Issues, https://github.com/Volgat/nexus-standardisation/issues
Keywords: cognitive-ai,neural-network,transformer,llm,world-model,multimodal,huggingface,pytorch
Classifier: Development Status :: 4 - Beta
Classifier: Intended Audience :: Developers
Classifier: Intended Audience :: Science/Research
Classifier: License :: Other/Proprietary License
Classifier: Operating System :: OS Independent
Classifier: Programming Language :: Python :: 3
Classifier: Programming Language :: Python :: 3.8
Classifier: Programming Language :: Python :: 3.9
Classifier: Programming Language :: Python :: 3.10
Classifier: Programming Language :: Python :: 3.11
Classifier: Programming Language :: Python :: 3.12
Classifier: Topic :: Scientific/Engineering :: Artificial Intelligence
Requires-Python: >=3.8
Requires-Dist: torch>=2.0.0
Requires-Dist: transformers>=4.35.0
Requires-Dist: datasets>=2.14.0
Requires-Dist: huggingface_hub>=0.19.0
Requires-Dist: accelerate>=0.24.0
Provides-Extra: dev
Requires-Dist: pytest>=7.0.0; extra == "dev"
Requires-Dist: black>=23.0.0; extra == "dev"
Requires-Dist: ruff>=0.1.0; extra == "dev"
Provides-Extra: training
Requires-Dist: wandb>=0.15.0; extra == "training"
Requires-Dist: tensorboard>=2.14.0; extra == "training"
Provides-Extra: vision
Requires-Dist: torchvision>=0.15.0; extra == "vision"
Requires-Dist: pillow>=9.0.0; extra == "vision"
Provides-Extra: audio
Requires-Dist: torchaudio>=2.0.0; extra == "audio"
Requires-Dist: librosa>=0.10.0; extra == "audio"
Provides-Extra: all
Requires-Dist: wandb>=0.15.0; extra == "all"
Requires-Dist: tensorboard>=2.14.0; extra == "all"
Requires-Dist: torchvision>=0.15.0; extra == "all"
Requires-Dist: pillow>=9.0.0; extra == "all"
Requires-Dist: torchaudio>=2.0.0; extra == "all"
Requires-Dist: librosa>=0.10.0; extra == "all"
Dynamic: author
Dynamic: home-page
Dynamic: requires-python
